lpslabtools/__init__.py
lpslabtools/spefileparser.py
lpslabtools-0.1.0.dist-info/LICENSE
lpslabtools-0.1.0.dist-info/METADATA
lpslabtools-0.1.0.dist-info/WHEEL
lpslabtools-0.1.0.dist-info/top_level.txt
lpslabtools-0.1.0.dist-info/RECORD
