Metadata-Version: 2.1
Name: lpslabtools
Version: 0.1.0
Summary: A tool to processing  spectrometer file in LPS-LENP
Author: HETAO
Author-email: 2300566779@qq.com
License: MIT
Classifier: Programming Language :: Python :: 3
Classifier: License :: OSI Approved :: MIT License
Classifier: Operating System :: OS Independent
License-File: LICENSE
